{
  "Filename": "tree-736885_1280.jpg",
  "Colors": [
    {
      "Hsv": {
        "H": 345.0,
        "S": 0.44444445,
        "V": 0.03529412
      },
      "Hex": "090506",
      "Fraction": 0.184165625
    },
    {
      "Hsv": {
        "H": 255.0,
        "S": 0.6,
        "V": 0.15686275
      },
      "Hex": "161028",
      "Fraction": 0.148640625
    },
    {
      "Hsv": {
        "H": 283.125,
        "S": 0.5614035,
        "V": 0.22352941
      },
      "Hex": "301939",
      "Fraction": 0.1463921875
    },
    {
      "Hsv": {
        "H": 319.56522,
        "S": 0.5897436,
        "V": 0.30588236
      },
      "Hex": "4E203F",
      "Fraction": 0.1378484375
    },
    {
      "Hsv": {
        "H": 333.42856,
        "S": 0.6363636,
        "V": 0.43137255
      },
      "Hex": "6E2847",
      "Fraction": 0.0888359375
    },
    {
      "Hsv": {
        "H": 307.82608,
        "S": 0.5609756,
        "V": 0.16078432
      },
      "Hex": "291226",
      "Fraction": 0.085665625
    },
    {
      "Hsv": {
        "H": 340.66666,
        "S": 0.6,
        "V": 0.5882353
      },
      "Hex": "963C59",
      "Fraction": 0.05393125
    },
    {
      "Hsv": {
        "H": 348.09525,
        "S": 0.6631579,
        "V": 0.74509805
      },
      "Hex": "BE4059",
      "Fraction": 0.0479890625
    },
    {
      "Hsv": {
        "H": 359.48718,
        "S": 0.5416667,
        "V": 0.84705883
      },
      "Hex": "D86364",
      "Fraction": 0.0456328125
    },
    {
      "Hsv": {
        "H": 346.15384,
        "S": 0.7222222,
        "V": 0.5647059
      },
      "Hex": "902840",
      "Fraction": 0.0355921875
    },
    {
      "Hsv": {
        "H": 359.61038,
        "S": 0.74757284,
        "V": 0.80784315
      },
      "Hex": "CE3435",
      "Fraction": 0.023215625
    },
    {
      "Hsv": {
        "H": 24.146341,
        "S": 0.338843,
        "V": 0.9490196
      },
      "Hex": "F2C1A0",
      "Fraction": 0.002090625
    }
  ]
}