{
  "Filename": "cat-4419763_1280.jpg",
  "Colors": [
    {
      "Hsv": {
        "H": 75.13043,
        "S": 0.65340906,
        "V": 0.6901961
      },
      "Hex": "93B03D",
      "Fraction": 0.27105,
      "MatchedColor": false
    },
    {
      "Hsv": {
        "H": 75.48387,
        "S": 0.5027027,
        "V": 0.7254902
      },
      "Hex": "A1B95C",
      "Fraction": 0.264509375,
      "MatchedColor": false
    },
    {
      "Hsv": {
        "H": 42.22222,
        "S": 0.6044776,
        "V": 0.5254902
      },
      "Hex": "866E35",
      "Fraction": 0.1478015625,
      "MatchedColor": false
    },
    {
      "Hsv": {
        "H": 43.5,
        "S": 0.85106385,
        "V": 0.18431373
      },
      "Hex": "2F2407",
      "Fraction": 0.1023484375,
      "MatchedColor": false
    },
    {
      "Hsv": {
        "H": 67.5,
        "S": 0.94623655,
        "V": 0.3647059
      },
      "Hex": "525D05",
      "Fraction": 0.0597359375,
      "MatchedColor": false
    },
    {
      "Hsv": {
        "H": 48.979595,
        "S": 0.51578945,
        "V": 0.37254903
      },
      "Hex": "5F562E",
      "Fraction": 0.0561875,
      "MatchedColor": false
    },
    {
      "Hsv": {
        "H": 75.789474,
        "S": 0.2984293,
        "V": 0.7490196
      },
      "Hex": "B0BF86",
      "Fraction": 0.052840625,
      "MatchedColor": false
    },
    {
      "Hsv": {
        "H": 42.666668,
        "S": 0.31690142,
        "V": 0.5568628
      },
      "Hex": "8E8161",
      "Fraction": 0.0455265625,
      "MatchedColor": false
    }
  ]
}